LICENSE
MANIFEST.in
README.md
requirements.txt
setup.cfg
setup.py
eegeolab/__init__.py
eegeolab/calculators.py
eegeolab.egg-info/PKG-INFO
eegeolab.egg-info/SOURCES.txt
eegeolab.egg-info/dependency_links.txt
eegeolab.egg-info/not-zip-safe
eegeolab.egg-info/requires.txt
eegeolab.egg-info/top_level.txt
tests/test_calculators.py